autoPathTv.py
checkFilms.py
checkTvEps.py
filename_config.py
setup.py
checkTvEps.egg-info/PKG-INFO
checkTvEps.egg-info/SOURCES.txt
checkTvEps.egg-info/dependency_links.txt
checkTvEps.egg-info/entry_points.txt
checkTvEps.egg-info/top_level.txt