Metadata-Version: 1.0
Name: checkTvEps
Version: 0.2
Summary: A collection of utilties to verify TV episodes match a naming scheme
Home-page: http://github.com/dbr/checktveps/tree/master
Author: dbr/Ben
Author-email: UNKNOWN
License: GPLv2
Platform: UNKNOWN
Classifier: Environment :: Console
Classifier: Intended Audience :: End Users/Desktop
Classifier: License :: OSI Approved :: GNU General Public License (GPL)
Classifier: Natural Language :: English
Classifier: Operating System :: OS Independent
Classifier: Programming Language :: Python
Classifier: Topic :: Multimedia
Classifier: Topic :: Utilities
